subito/__init__.py
subito/operations/__init__.py
subito/operations/operation.py
subito/operations/subscription.py
subito/service.py
subito-0.1.6.dist-info/WHEEL
subito-0.1.6.dist-info/METADATA
subito-0.1.6.dist-info/RECORD
