Metadata-Version: 2.1
Name: subito
Version: 0.1.6
Summary: Quickly create stateless microservices based on GraphQL subscription messages.
Home-page: https://github.com/srbiotik/subito
License: MIT
Author: Milos Grujic
Author-email: srbiotik@gmail.com
Requires-Python: >=3.8,<4.0
Classifier: License :: OSI Approved :: MIT License
Classifier: Programming Language :: Python :: 3
Classifier: Programming Language :: Python :: 3.8
Requires-Dist: gql (>=3.0.0-alpha.1,<4.0.0)
Requires-Dist: python-box (>=5.1.1,<6.0.0)
Requires-Dist: tinydb (>=4.1.1,<5.0.0)
Project-URL: Repository, https://github.com/srbiotik/subito
